{
  "skins": [
    {
      "id": 1001,
      "name": "Normal",
      "shader_name": "Snake/TransparentWavy",
      "texture_name": "",
      "normal_tex_name": "",
      "main_size": 0.125,
      "second_size": 0.025
    },
    {
      "id": 1002,
      "name": "Withering Liquid",
      "shader_name": "Snake/Wither",
      "texture_name": "",
      "normal_tex_name": "SKIN_WITHER_NORMAL",
      "main_size": 0.125,
      "second_size": 0.125
    },
    {
      "id": 2001,
      "name": "Rainbow Bubble",
      "shader_name": "Snake/RainbowBubble",
      "texture_name": "SKIN_BUBBLE_MAIN",
      "normal_tex_name": "",
      "main_size": 0.125,
      "second_size": 0.075
    }
  ]
}
